docs/gen_reference_page.py
docs/index.md
genlm_grammar/__init__.py
genlm_grammar/cfg.py
genlm_grammar/cfglm.py
genlm_grammar/chart.py
genlm_grammar/fst.py
genlm_grammar/lark_interface.py
genlm_grammar/linear.py
genlm_grammar/lm.py
genlm_grammar/semiring.py
genlm_grammar/util.py
genlm_grammar/parse/__init__.py
genlm_grammar/parse/cky.py
genlm_grammar/parse/earley.py
genlm_grammar/parse/earley_rescaled.py
genlm_grammar/wfsa/__init__.py
genlm_grammar/wfsa/base.py
genlm_grammar/wfsa/field_wfsa.py
genlm_grammar-0.1.0.dist-info/licenses/LICENSE
tests/examples.py
tests/test_byte_wfsa.py
tests/test_earley.py
tests/test_earley_rescaled.py
tests/test_expectation.py
tests/test_fst.py
tests/test_intersection.py
tests/test_lark_interface.py
tests/test_linear.py
tests/test_prefix.py
tests/test_wcfg.py
tests/test_wfsa_field.py
tests/test_wfsa_semiring.py
genlm_grammar-0.1.0.dist-info/METADATA
genlm_grammar-0.1.0.dist-info/WHEEL
genlm_grammar-0.1.0.dist-info/top_level.txt
genlm_grammar-0.1.0.dist-info/RECORD
