Metadata-Version: 2.4
Name: genlm-grammar
Version: 0.1.0
Author: The GenLM Team
Requires-Python: >=3.10
License-File: LICENSE
Requires-Dist: frozendict
Requires-Dist: interegular
Requires-Dist: lark
Requires-Dist: nltk
Requires-Dist: numpy
Requires-Dist: arsenal
Requires-Dist: IPython
Requires-Dist: graphviz
Requires-Dist: pandas
Provides-Extra: test
Requires-Dist: coverage; extra == "test"
Requires-Dist: pytest; extra == "test"
Requires-Dist: pytest-benchmark; extra == "test"
Provides-Extra: docs
Requires-Dist: mkdocs; extra == "docs"
Requires-Dist: mkdocstrings[python]; extra == "docs"
Requires-Dist: mkdocs-material; extra == "docs"
Requires-Dist: mkdocs-gen-files; extra == "docs"
Requires-Dist: mkdocs-literate-nav; extra == "docs"
Requires-Dist: mkdocs-section-index; extra == "docs"
Dynamic: license-file
